qry_doc/__init__.py
qry_doc/ai_adapter.py
qry_doc/ai_builder.py
qry_doc/asset_manager.py
qry_doc/assets/__init__.py
qry_doc/assets/default_logo.png
qry_doc/chart_config.py
qry_doc/chart_generator.py
qry_doc/chart_manager.py
qry_doc/core.py
qry_doc/cover_builder.py
qry_doc/csv_exporter.py
qry_doc/data_source.py
qry_doc/exceptions.py
qry_doc/py.typed
qry_doc/report_generator.py
qry_doc/report_preset.py
qry_doc/report_template.py
qry_doc/template_builder.py
qry_doc/text_element.py
qry_doc/validators.py
qry_doc-0.1.51.dist-info/WHEEL
qry_doc-0.1.51.dist-info/METADATA
qry_doc-0.1.51.dist-info/RECORD
