Metadata-Version: 2.3
Name: qry-doc
Version: 0.1.51
Summary: Motor de análisis generativo que transforma el lenguaje natural en código ejecutable, visualizaciones y reportes PDF profesionales.
Author: danro-dev
Author-email: danro-dev <drgrassnk445@gmail.com>
Requires-Dist: matplotlib>=3.7.5
Requires-Dist: pandasai>=3.0.0
Requires-Dist: pillow>=10.4.0
Requires-Dist: reportlab>=4.4.7
Requires-Dist: sqlalchemy>=2.0.0
Requires-Dist: pandasai-openai>=0.1.0 ; extra == 'all'
Requires-Dist: pandasai-litellm>=0.0.1 ; extra == 'all'
Requires-Dist: psycopg2-binary>=2.9.0 ; extra == 'all'
Requires-Dist: langchain>=0.3.0 ; extra == 'all'
Requires-Dist: langchain-core>=0.3.0 ; extra == 'all'
Requires-Dist: hypothesis>=6.148.8 ; extra == 'dev'
Requires-Dist: pytest>=9.0.2 ; extra == 'dev'
Requires-Dist: pytest-cov>=7.0.0 ; extra == 'dev'
Requires-Dist: langchain>=0.3.0 ; extra == 'langchain'
Requires-Dist: langchain-core>=0.3.0 ; extra == 'langchain'
Requires-Dist: pandasai-litellm>=0.0.1 ; extra == 'litellm'
Requires-Dist: pymysql>=1.0.0 ; extra == 'mysql'
Requires-Dist: pandasai-openai>=0.1.0 ; extra == 'openai'
Requires-Dist: psycopg2-binary>=2.9.0 ; extra == 'postgres'
Requires-Python: >=3.11
Provides-Extra: all
Provides-Extra: dev
Provides-Extra: langchain
Provides-Extra: litellm
Provides-Extra: mysql
Provides-Extra: openai
Provides-Extra: postgres
